KOMPAS_tools/KompasClass.py
KOMPAS_tools/Serpinsky.py
KOMPAS_tools/Test.py
KOMPAS_tools/__init__.py
KOMPAS_tools-0.3.dist-info/METADATA
KOMPAS_tools-0.3.dist-info/WHEEL
KOMPAS_tools-0.3.dist-info/top_level.txt
KOMPAS_tools-0.3.dist-info/RECORD
