Metadata-Version: 2.1
Name: KOMPAS-tools
Version: 0.3
Summary: This library contains tools for KOMPAS 3D automation
Home-page: https://github.com/Mikarisar/KOMPAS_tools
Author: Mikarisar
Author-email: mikarisar@gmail.com
Project-URL: GitHub, https://github.com/Mikarisar/KOMPAS_tools
Keywords: cad drawing kompas kompas3d automation engineering
Classifier: Programming Language :: Python :: 3.11
Classifier: License :: OSI Approved :: MIT License
Classifier: Operating System :: Microsoft :: Windows
Requires-Python: >=3.6
Requires-Dist: pywin32
Requires-Dist: numpy
